passwordgenerator/__init__.py
passwordgenerator/__main__.py
passwordgenerator/pwgenerator.py
passwordgenerator/data/__init__.py
passwordgenerator/data/english.py
passwordgenerator-1.4.dist-info/LICENSE
passwordgenerator-1.4.dist-info/METADATA
passwordgenerator-1.4.dist-info/WHEEL
passwordgenerator-1.4.dist-info/entry_points.txt
passwordgenerator-1.4.dist-info/top_level.txt
passwordgenerator-1.4.dist-info/RECORD
