Metadata-Version: 1.1
Name: passwordgenerator
Version: 1.4
Summary: Passwords easy for humans, hard for computers
Home-page: https://github.com/gabfl/password-generator-py/
Author: Gabriel Bordeaux
Author-email: pypi@gab.lc
License: MIT
Platform: UNKNOWN
Classifier: Topic :: Security
Classifier: License :: OSI Approved :: MIT License
Classifier: Operating System :: MacOS
Classifier: Operating System :: POSIX :: Linux
Classifier: Natural Language :: English
Classifier: Programming Language :: Python :: 2.7
Classifier: Programming Language :: Python :: 3
Classifier: Programming Language :: Python
Classifier: Development Status :: 5 - Production/Stable
